setup.py
django_sqlpaginator.egg-info/PKG-INFO
django_sqlpaginator.egg-info/SOURCES.txt
django_sqlpaginator.egg-info/dependency_links.txt
django_sqlpaginator.egg-info/requires.txt
django_sqlpaginator.egg-info/top_level.txt
sqlpaginator/__init__.py
sqlpaginator/paginator.py
sqlpaginator/version.py