Metadata-Version: 1.0
Name: django-sqlpaginator
Version: 0.1.3
Summary: django app that does pagination and ordering using raw
Home-page: https://github.com/bulkan/django-sqlpaginator
Author: Bulkan Evcimen
Author-email: bulkan@gmail.com
License: UNKNOWN
Platform: UNKNOWN
Classifier: Development Status :: 5 - Production/Stable
Classifier: Intended Audience :: Developers
Classifier: Natural Language :: English
Classifier: Programming Language :: Python
Classifier: Programming Language :: Python :: 2.6
Classifier: Programming Language :: Python :: 2.7
